<?xml version='1.0' encoding='UTF-8'?>
<!DOCTYPE beans PUBLIC '-//SPRING//DTD BEAN//EN' 'http://www.springframework.org/dtd/spring-beans.dtd'>
<beans>

	<bean id="idocs.module-component.cardlets-cmobject" parent="idocs.import-spaces">
		<property name="name" value="cardlets-cmobject" />
		<property name="description" value="Common Cardlets" />
		<property name="sinceVersion" value="0.0.1" />
		<property name="appliesFromVersion" value="0.0.1" />
		<property name="dependsOn">
			<list>
				<ref bean="idocs.module-component.system-journals.cardlets" />
			</list>
		</property>
		<property name="bootstrapViews">
			<list>
				<props>
					<prop key="path">/app:company_home/app:dictionary/cm:cardlets</prop>
					<prop key="location">alfresco/templates/bootstrap/ru/citeck/cardlets/cardlet.xml</prop>
					<prop key="messages">alfresco/module/idocs-repo/bootstrap/cardlets/cmobject/node-header</prop>
				</props>
				<props>
					<prop key="path">/app:company_home/app:dictionary/cm:cardlets</prop>
					<prop key="location">alfresco/templates/bootstrap/ru/citeck/cardlets/cardlet.xml</prop>
					<prop key="messages">alfresco/module/idocs-repo/bootstrap/cardlets/cmobject/history</prop>
				</props>
				<props>
					<prop key="path">/app:company_home/app:dictionary/cm:cardlets</prop>
					<prop key="location">alfresco/templates/bootstrap/ru/citeck/cardlets/cardlet.xml</prop>
					<prop key="messages">alfresco/module/idocs-repo/bootstrap/cardlets/cmobject/comments</prop>
				</props>
				<props>
					<prop key="path">/app:company_home/app:dictionary/cm:cardlets</prop>
					<prop key="location">alfresco/templates/bootstrap/ru/citeck/cardlets/cardlet.xml</prop>
					<prop key="messages">alfresco/module/idocs-repo/bootstrap/cardlets/cmobject/actions</prop>
				</props>
				<props>
					<prop key="path">/app:company_home/app:dictionary/cm:cardlets</prop>
					<prop key="location">alfresco/templates/bootstrap/ru/citeck/cardlets/cardlet.xml</prop>
					<prop key="messages">alfresco/module/idocs-repo/bootstrap/cardlets/cmobject/metadata</prop>
				</props>
				<props>
					<prop key="path">/app:company_home/app:dictionary/cm:cardlets</prop>
					<prop key="location">alfresco/templates/bootstrap/ru/citeck/cardlets/cardlet.xml</prop>
					<prop key="messages">alfresco/module/idocs-repo/bootstrap/cardlets/cmobject/associations</prop>
				</props>
				<props>
					<prop key="path">/app:company_home/app:dictionary/cm:cardlets</prop>
					<prop key="location">alfresco/templates/bootstrap/ru/citeck/cardlets/cardlet.xml</prop>
					<prop key="messages">alfresco/module/idocs-repo/bootstrap/cardlets/cmobject/card-templates</prop>
				</props>
			</list>
		</property>
	</bean>

	<bean id="idocs.module-component.cardlets-cmobject2" parent="idocs.import-spaces">
		<property name="name" value="cardlets-cmobject2" />
		<property name="description" value="Common Cardlets" />
		<property name="sinceVersion" value="2.10.0" />
		<property name="appliesFromVersion" value="2.10.0" />
		<property name="dependsOn">
			<list>
				<ref bean="idocs.module-component.system-journals.cardlets" />
			</list>
		</property>
		<property name="bootstrapViews">
			<list>
				<props>
					<prop key="path">/app:company_home/app:dictionary/cm:cardlets</prop>
					<prop key="location">alfresco/templates/bootstrap/ru/citeck/cardlets/cardlet.xml</prop>
					<prop key="messages">alfresco/module/idocs-repo/bootstrap/cardlets/cmobject/document-status</prop>
				</props>
				<props>
					<prop key="path">/app:company_home/app:dictionary/cm:cardlets</prop>
					<prop key="location">alfresco/templates/bootstrap/ru/citeck/cardlets/cardlet.xml</prop>
					<prop key="messages">alfresco/module/idocs-repo/bootstrap/cardlets/cmobject/current-tasks</prop>
				</props>
			</list>
		</property>
	</bean>

	<bean id="idocs.module-component.cardlets-tabs" parent="idocs.import-spaces">
		<property name="name" value="cardlets-tabs" />
		<property name="description" value="Tabs Cardlets" />
		<property name="sinceVersion" value="0.0.1" />
		<property name="appliesFromVersion" value="0.0.1" />
		<!--property name="executeOnceOnly" value="false" /-->
		<property name="dependsOn">
			<list>
				<ref bean="idocs.module-component.cardlets-cmobject" />
				<ref bean="idocs.module-component.system-journals.cardmodes" />
			</list>
		</property>
		<property name="bootstrapViews">
			<list>
				<props>
					<prop key="path">/app:company_home/app:dictionary/cm:cardmodes</prop>
					<prop key="location">alfresco/templates/bootstrap/ru/citeck/cardlets/card-mode.xml</prop>
					<prop key="messages">alfresco/module/idocs-repo/bootstrap/cardlets/documents-mode</prop>
					<prop key="encoding">UTF-8</prop>
				</props>
				<props>
					<prop key="path">/app:company_home/app:dictionary/cm:cardlets</prop>
					<prop key="location">alfresco/templates/bootstrap/ru/citeck/cardlets/cardlet-all-modes.xml</prop>
					<prop key="messages">alfresco/module/idocs-repo/bootstrap/cardlets/cmobject/node-header</prop>
				</props>
				<props>
					<prop key="path">/app:company_home/app:dictionary/cm:cardlets</prop>
					<prop key="location">alfresco/templates/bootstrap/ru/citeck/cardlets/cardlet-with-mode.xml</prop>
					<prop key="messages">alfresco/module/idocs-repo/bootstrap/cardlets/cmobject/card-modes</prop>
				</props>
			</list>
		</property>
	</bean>

	<bean id="idocs.module-component.cardlets-content" parent="idocs.import-spaces">
		<property name="name" value="cardlets-content" />
		<property name="description" value="Content Cardlets" />
		<property name="sinceVersion" value="0.0.1" />
		<property name="appliesFromVersion" value="0.0.1" />
		<property name="dependsOn">
			<list>
				<ref bean="idocs.module-component.system-journals.cardlets" />
			</list>
		</property>
		<property name="bootstrapViews">
			<list>
				<props>
					<prop key="path">/app:company_home/app:dictionary/cm:cardlets</prop>
					<prop key="location">alfresco/templates/bootstrap/ru/citeck/cardlets/cardlet.xml</prop>
					<prop key="messages">alfresco/module/idocs-repo/bootstrap/cardlets/content/web-preview</prop>
				</props>
				<props>
					<prop key="path">/app:company_home/app:dictionary/cm:cardlets</prop>
					<prop key="location">alfresco/templates/bootstrap/ru/citeck/cardlets/cardlet.xml</prop>
					<prop key="messages">alfresco/module/idocs-repo/bootstrap/cardlets/content/document-tasks</prop>
				</props>
				<props>
					<prop key="path">/app:company_home/app:dictionary/cm:cardlets</prop>
					<prop key="location">alfresco/templates/bootstrap/ru/citeck/cardlets/cardlet.xml</prop>
					<prop key="messages">alfresco/module/idocs-repo/bootstrap/cardlets/content/supplementary-files</prop>
				</props>
				<props>
					<prop key="path">/app:company_home/app:dictionary/cm:cardlets</prop>
					<prop key="location">alfresco/templates/bootstrap/ru/citeck/cardlets/cardlet.xml</prop>
					<prop key="messages">alfresco/module/idocs-repo/bootstrap/cardlets/content/document-workflows</prop>
				</props>
				<props>
					<prop key="path">/app:company_home/app:dictionary/cm:cardlets</prop>
					<prop key="location">alfresco/templates/bootstrap/ru/citeck/cardlets/cardlet.xml</prop>
					<prop key="messages">alfresco/module/idocs-repo/bootstrap/cardlets/content/inactive-document-workflows</prop>
				</props>
				<props>
					<prop key="path">/app:company_home/app:dictionary/cm:cardlets</prop>
					<prop key="location">alfresco/templates/bootstrap/ru/citeck/cardlets/cardlet.xml</prop>
					<prop key="messages">alfresco/module/idocs-repo/bootstrap/cardlets/content/document-versions</prop>
				</props>
				<props>
					<prop key="path">/app:company_home/app:dictionary/cm:cardlets</prop>
					<prop key="location">alfresco/templates/bootstrap/ru/citeck/cardlets/cardlet.xml</prop>
					<prop key="messages">alfresco/module/idocs-repo/bootstrap/cardlets/content/document-versions-comparison</prop>
				</props>
			</list>
		</property>
	</bean>

	<bean id="idocs.module-component.cardlets-datalistitem" parent="idocs.import-spaces">
		<property name="name" value="cardlets-datalistitem" />
		<property name="description" value="DataListItem Cardlets" />
		<property name="sinceVersion" value="2.9.0" />
		<property name="appliesFromVersion" value="2.9.0" />
		<property name="dependsOn">
			<list>
				<ref bean="idocs.module-component.system-journals.cardlets" />
			</list>
		</property>
		<property name="bootstrapViews">
			<list>
				<props>
					<prop key="path">/app:company_home/app:dictionary/cm:cardlets</prop>
					<prop key="location">alfresco/templates/bootstrap/ru/citeck/cardlets/cardlet.xml</prop>
					<prop key="messages">alfresco/module/idocs-repo/bootstrap/cardlets/datalistitem/web-preview</prop>
				</props>
			</list>
		</property>
	</bean>

	<bean id="idocs.module-component.cardlets-new-forms" parent="idocs.import-spaces">
		<property name="name" value="cardlets-new-forms" />
		<property name="description" value="Cardlets for new forms" />
		<property name="sinceVersion" value="2.11.0" />
		<property name="appliesFromVersion" value="2.11.0" />
		<property name="dependsOn">
			<list>
				<ref bean="idocs.module-component.cardlets-cmobject" />
			</list>
		</property>
		<property name="bootstrapViews">
			<list>
				<props>
					<prop key="path">/app:company_home/app:dictionary/cm:cardlets</prop>
					<prop key="location">alfresco/templates/bootstrap/ru/citeck/cardlets/cardlet.xml</prop>
					<prop key="messages">alfresco/module/idocs-repo/bootstrap/cardlets/cmobject/node-view</prop>
				</props>
				<props>
					<prop key="path">/app:company_home/app:dictionary/cm:cardlets</prop>
					<prop key="location">alfresco/templates/bootstrap/ru/citeck/cardlets/cardlet-update.xml</prop>
					<prop key="messages">alfresco/module/idocs-repo/bootstrap/cardlets/cmobject/metadata</prop>
				</props>
			</list>
		</property>
	</bean>
	
	<bean id="idocs.module-component.cardlets-current-tasks" parent="idocs.import-spaces">
		<property name="name" value="cardlets-current-tasks" />
		<property name="description" value="current-tasks Cardlets" />
		<property name="sinceVersion" value="2.9.0" />
		<property name="appliesFromVersion" value="2.9.0" />
		<property name="dependsOn">
			<list>
				<ref bean="idocs.module-component.system-journals.cardlets" />
			</list>
		</property>
		<property name="bootstrapViews">
			<list>
				<props>
					<prop key="path">/app:company_home/app:dictionary/cm:cardlets</prop>
					<prop key="location">alfresco/templates/bootstrap/ru/citeck/cardlets/cardlet.xml</prop>
					<prop key="messages">alfresco/module/idocs-repo/bootstrap/cardlets/cmobject/current-tasks</prop>
				</props>
			</list>
		</property>
	</bean>

	<bean id="idocs.module-component.cardlets-metadata" parent="idocs.import-spaces">
		<property name="name" value="cardlets-metadata" />
		<property name="description" value="Metadata Cardlets for non content objects" />
		<property name="sinceVersion" value="2.12.0" />
		<property name="appliesFromVersion" value="2.12.0" />
		<property name="dependsOn">
			<list>
				<ref bean="idocs.module-component.system-journals.cardlets" />
			</list>
		</property>
		<property name="bootstrapViews">
			<list>
				<props>
					<prop key="path">/app:company_home/app:dictionary/cm:cardlets</prop>
					<prop key="location">alfresco/templates/bootstrap/ru/citeck/cardlets/cardlet.xml</prop>
					<prop key="messages">alfresco/module/idocs-repo/bootstrap/cardlets/datalistitem/metadata</prop>
				</props>
				<props>
					<prop key="path">/app:company_home/app:dictionary/cm:cardlets</prop>
					<prop key="location">alfresco/templates/bootstrap/ru/citeck/cardlets/cardlet.xml</prop>
					<prop key="messages">alfresco/module/idocs-repo/bootstrap/cardlets/cmfolder/metadata</prop>
				</props>
			</list>
		</property>
	</bean>

	<bean id="idocs.module-component.cardlets-node-view" parent="idocs.import-spaces">
		<property name="name" value="cardlets-node-view" />
		<property name="description" value="node-view Cardlets for non content objects" />
		<property name="sinceVersion" value="2.12.0" />
		<property name="appliesFromVersion" value="2.12.0" />
		<property name="dependsOn">
			<list>
				<ref bean="idocs.module-component.system-journals.cardlets" />
			</list>
		</property>
		<property name="bootstrapViews">
			<list>
				<props>
					<prop key="path">/app:company_home/app:dictionary/cm:cardlets</prop>
					<prop key="location">alfresco/templates/bootstrap/ru/citeck/cardlets/cardlet.xml</prop>
					<prop key="messages">alfresco/module/idocs-repo/bootstrap/cardlets/datalistitem/node-view</prop>
				</props>
				<props>
					<prop key="path">/app:company_home/app:dictionary/cm:cardlets</prop>
					<prop key="location">alfresco/templates/bootstrap/ru/citeck/cardlets/cardlet.xml</prop>
					<prop key="messages">alfresco/module/idocs-repo/bootstrap/cardlets/cmfolder/node-view</prop>
				</props>
			</list>
		</property>
	</bean>

	<bean id="idocs.module-component.cardlets-document-supervisors" parent="idocs.import-spaces">
		<property name="name" value="cardlets-document-supervisors" />
		<property name="description" value="Document supervisors cardlet" />
		<property name="sinceVersion" value="2.11.0" />
		<property name="appliesFromVersion" value="2.11.0" />
		<property name="dependsOn">
			<list>
				<ref bean="idocs.module-component.system-journals.cardlets" />
			</list>
		</property>
		<property name="bootstrapViews">
			<list>
				<props>
					<prop key="path">/app:company_home/app:dictionary/cm:cardlets</prop>
					<prop key="location">alfresco/templates/bootstrap/ru/citeck/cardlets/cardlet.xml</prop>
					<prop key="messages">alfresco/module/idocs-repo/bootstrap/cardlets/cmobject/document-supervisors</prop>
				</props>
			</list>
		</property>
	</bean>
</beans>